[
    {
        "channel": {
            "username": "freev2raygood",
            "title": "Freev2ray",
            "logo": "https:\/\/raw.githubusercontent.com\/alihusainsorathiya\/v2gram\/main\/modules\/channels\/freev2raygood.jpg"
        },
        "type": "vless",
        "config": "vless:\/\/5889069c-5d0a-442b-8a2f-571e821153cf@d1c2d1cvq5lwn1.cloudfront.net:443?path=\/current_time&amp;security=tls&amp;encryption=none&amp;type=ws&amp;sni=d1c2d1cvq5lwn1.cloudfront.net#@freev2raygood| AHS -\ud83c\uddfa\ud83c\uddf8|7.32",
        "time": "2025-08-11 02:58:08"
    },
    {
        "channel": {
            "username": "freev2raygood",
            "title": "Freev2ray",
            "logo": "https:\/\/raw.githubusercontent.com\/alihusainsorathiya\/v2gram\/main\/modules\/channels\/freev2raygood.jpg"
        },
        "type": "vless",
        "config": "vless:\/\/5889069c-5d0a-442b-8a2f-571e821153cf@d3ko5fk551z9sn.cloudfront.net:443?path=\/current_time&amp;security=tls&amp;encryption=none&amp;type=ws&amp;sni=d3ko5fk551z9sn.cloudfront.net#@freev2raygood| AHS -\ud83c\uddfa\ud83c\uddf8|6.89",
        "time": "2025-08-11 02:58:07"
    },
    {
        "channel": {
            "username": "v2rayngrit",
            "title": "\ud80c\udd02\uaa9c2\ud835\ude33\uaa96\uaa97\uaa80\u19c1\ud835\ude33\ud835\udcf2\ud835\udcfd\ud80c\udd83",
            "logo": "https:\/\/raw.githubusercontent.com\/alihusainsorathiya\/v2gram\/main\/modules\/channels\/v2rayngrit.jpg"
        },
        "type": "vless",
        "config": "vless:\/\/c39a101c-0a7b-4940-8e6a-f8346d70b24b@91.99.221.206:443?security=none&amp;encryption=none&amp;host=zula.ir&amp;headerType=http&amp;type=tcp#@v2rayngrit| AHS -\ud83c\udde9\ud83c\uddea|95.34",
        "time": "2025-08-11 02:57:35"
    },
    {
        "channel": {
            "username": "v2rayngrit",
            "title": "\ud80c\udd02\uaa9c2\ud835\ude33\uaa96\uaa97\uaa80\u19c1\ud835\ude33\ud835\udcf2\ud835\udcfd\ud80c\udd83",
            "logo": "https:\/\/raw.githubusercontent.com\/alihusainsorathiya\/v2gram\/main\/modules\/channels\/v2rayngrit.jpg"
        },
        "type": "vless",
        "config": "vless:\/\/e66beedb-dd44-47f0-baf8-7ba947d919d0@91.99.126.77:8443?mode=stream-one&amp;path=\/xhttp&amp;security=none&amp;encryption=none&amp;type=xhttp#@v2rayngrit| AHS -\ud83c\udde9\ud83c\uddea|95.26",
        "time": "2025-08-11 02:57:35"
    },
    {
        "channel": {
            "username": "v2rayngrit",
            "title": "\ud80c\udd02\uaa9c2\ud835\ude33\uaa96\uaa97\uaa80\u19c1\ud835\ude33\ud835\udcf2\ud835\udcfd\ud80c\udd83",
            "logo": "https:\/\/raw.githubusercontent.com\/alihusainsorathiya\/v2gram\/main\/modules\/channels\/v2rayngrit.jpg"
        },
        "type": "ss",
        "config": "ss:\/\/YWVzLTI1Ni1nY206aUhhcEdZOFhvVw3D3A==@154.44.15.133:44642#@v2rayngrit| AHS -\ud83c\uddfa\ud83c\uddf8|56.05",
        "time": "2025-08-11 02:57:34"
    },
    {
        "channel": {
            "username": "v2rayngrit",
            "title": "\ud80c\udd02\uaa9c2\ud835\ude33\uaa96\uaa97\uaa80\u19c1\ud835\ude33\ud835\udcf2\ud835\udcfd\ud80c\udd83",
            "logo": "https:\/\/raw.githubusercontent.com\/alihusainsorathiya\/v2gram\/main\/modules\/channels\/v2rayngrit.jpg"
        },
        "type": "ss",
        "config": "ss:\/\/Y2hhY2hhMjAtaWV0Zi1wb2x5MTMwNTpmOGY3YUN6Y1BLYnNGOHAz@92.118.205.228:990#@v2rayngrit| AHS -\ud83c\uddf5\ud83c\uddf1|112.42",
        "time": "2025-08-11 02:57:34"
    },
    {
        "channel": {
            "username": "v2rayngrit",
            "title": "\ud80c\udd02\uaa9c2\ud835\ude33\uaa96\uaa97\uaa80\u19c1\ud835\ude33\ud835\udcf2\ud835\udcfd\ud80c\udd83",
            "logo": "https:\/\/raw.githubusercontent.com\/alihusainsorathiya\/v2gram\/main\/modules\/channels\/v2rayngrit.jpg"
        },
        "type": "ss",
        "config": "ss:\/\/Y2hhY2hhMjAtaWV0Zi1wb2x5MTMwNTpvWklvQTY5UTh5aGNRVjhrYTNQYTNB@45.87.175.35:8080#@v2rayngrit| AHS -\ud83c\uddf1\ud83c\uddf9|85.86",
        "time": "2025-08-11 02:57:33"
    },
    {
        "channel": {
            "username": "hope_net",
            "title": "\ud83d\udd4a Hope Net",
            "logo": "https:\/\/raw.githubusercontent.com\/alihusainsorathiya\/v2gram\/main\/modules\/channels\/hope_net.jpg"
        },
        "type": "ss",
        "config": "ss:\/\/Y2hhY2hhMjAtaWV0Zi1wb2x5MTMwNTpVRGNqWVE2WjZBSVd4VmlacHF5T21P@46.246.98.155:44013#@hope_net| AHS -\ud83c\uddf8\ud83c\uddea|101.46",
        "time": "2025-08-11 02:57:16"
    },
    {
        "channel": {
            "username": "hope_net",
            "title": "\ud83d\udd4a Hope Net",
            "logo": "https:\/\/raw.githubusercontent.com\/alihusainsorathiya\/v2gram\/main\/modules\/channels\/hope_net.jpg"
        },
        "type": "trojan",
        "config": "trojan:\/\/blue2024@104.16.80.177:443?allowInsecure=1&amp;sni=hb.lii2010.us.kg&amp;ws=1&amp;wspath=\/?ed=2560#\ud83d\udea9|@hope_net| AHS -6.67",
        "time": "2025-08-11 02:57:14"
    },
    {
        "channel": {
            "username": "hope_net",
            "title": "\ud83d\udd4a Hope Net",
            "logo": "https:\/\/raw.githubusercontent.com\/alihusainsorathiya\/v2gram\/main\/modules\/channels\/hope_net.jpg"
        },
        "type": "trojan",
        "config": "trojan:\/\/blue2024@craig.ns.cloudflare.com:443?allowInsecure=1&amp;sni=tb.promote.icu&amp;ws=1&amp;wspath=\/?ed=2560#\ud83d\udea9|@hope_net| AHS -26.54",
        "time": "2025-08-11 02:57:14"
    },
    {
        "channel": {
            "username": "Parsashonam",
            "title": "Parsashonam | \u0641\u06cc\u0644\u062a\u0631\u0634\u06a9\u0646 \u0631\u0627\u06cc\u06af\u0627\u0646 | V2Ray",
            "logo": "https:\/\/raw.githubusercontent.com\/alihusainsorathiya\/v2gram\/main\/modules\/channels\/Parsashonam.jpg"
        },
        "type": "reality",
        "config": "vless:\/\/Parsashonam-297@91.99.16.244:443?mode=auto&amp;path=\/Parsashonam-Parsashonam-Parsashonam-Parsashonam-Parsashonam-Parsashonam&amp;security=reality&amp;encryption=none&amp;pbk=sa5RHNjAAD3hYv4OU_YYU08gRUsmPs5JdZES5Xy3pn8&amp;fp=chrome&amp;spx=\/&amp;type=xhttp&amp;sni=Google.com&amp;sid=61e683d41fdb#REALITY|@Parsashonam|\ud83c\udde9\ud83c\uddea|96.05",
        "time": "2025-08-11 02:57:11"
    },
    {
        "channel": {
            "username": "Parsashonam",
            "title": "Parsashonam | \u0641\u06cc\u0644\u062a\u0631\u0634\u06a9\u0646 \u0631\u0627\u06cc\u06af\u0627\u0646 | V2Ray",
            "logo": "https:\/\/raw.githubusercontent.com\/alihusainsorathiya\/v2gram\/main\/modules\/channels\/Parsashonam.jpg"
        },
        "type": "vless",
        "config": "vless:\/\/Parsashonam-296@185.146.173.39:8880?type=httpupgrade&amp;path=\/Parsashonam-Parsashonam-Parsashonam\/?ed=2056&amp;host=De.Parsashonam.CfD.&amp;security=none#@Parsashonam| AHS -\ud83c\uddf8\ud83c\uddea|5.35",
        "time": "2025-08-11 02:57:10"
    },
    {
        "channel": {
            "username": "V2rayngninja",
            "title": "\ud80c\udda9Ninja VPN\ud80c\uddaa\u200c",
            "logo": "https:\/\/raw.githubusercontent.com\/alihusainsorathiya\/v2gram\/main\/modules\/channels\/V2rayngninja.jpg"
        },
        "type": "reality",
        "config": "vless:\/\/97d53a59-918e-45fc-bc5d-ba487f090cc1@80.240.23.101:443?type=xhttp&amp;path=\/Dota2?ed=2048&amp;host=&amp;mode=auto&amp;security=reality&amp;pbk=HhI0Y1IV5Vks0OqsV6N4Csvaivc1BH_IzoSbw5Ii_3o&amp;fp=randomized&amp;sni=hundleymechanical.com&amp;sid=008c74&amp;spx=\/#REALITY|@V2rayngninja|\ud83c\udde9\ud83c\uddea|91.89",
        "time": "2025-08-11 02:56:47"
    },
    {
        "channel": {
            "username": "proxy_kafee",
            "title": "\ud83c\udf6e Kafe Proxy \ud83c\udf6e Client Pro V2RayNG VPN",
            "logo": "https:\/\/raw.githubusercontent.com\/alihusainsorathiya\/v2gram\/main\/modules\/channels\/proxy_kafee.jpg"
        },
        "type": "reality",
        "config": "vless:\/\/7edc9161-fa59-45ae-b9e9-80ef4bceb68e@85.9.203.125:36563?security=reality&amp;encryption=none&amp;pbk=tPpkzwOVa4li8CurZc07pnxl8ytBUm9x4b9TBP99h00&amp;headerType=none&amp;fp=chrome&amp;type=tcp&amp;flow=xtls-rprx-vision&amp;sni=expedia.com&amp;sid=c294d6ba98e6a7#REALITY|@proxy_kafee|\ud83c\uddeb\ud83c\uddee|91.31",
        "time": "2025-08-11 02:56:34"
    },
    {
        "channel": {
            "username": "vpn_tehran",
            "title": "V2rayNG \u0645\u0631\u06a9\u0632 \u062a\u062e\u0635\u0635\u06cc",
            "logo": "https:\/\/raw.githubusercontent.com\/alihusainsorathiya\/v2gram\/main\/modules\/channels\/vpn_tehran.jpg"
        },
        "type": "vmess",
        "config": "vmess:\/\/eyJhZGQiOiI2Mi4xNDYuMjM1LjE5MyIsImFpZCI6IjAiLCJhbHBuIjoiIiwiZnAiOiIiLCJob3N0IjoiIiwiaWQiOiJjZmM1YTg3Zi0zYzEzLTRlMjUtYjU1Ni0xNzZjZGQ2YjVjNmEiLCJuZXQiOiJ0Y3AiLCJwYXRoIjoiIiwicG9ydCI6IjI4MDExIiwicHMiOiJAdnBuX3RlaHJhbnwgQUhTIC1cdWQ4M2NcdWRkZjhcdWQ4M2NcdWRkZWN8MjQyLjMyIiwic2N5IjoiYXV0byIsInNuaSI6IiIsInRscyI6IiIsInR5cGUiOiJub25lIiwidiI6IjIifQ==",
        "time": "2025-08-11 02:56:28"
    },
    {
        "channel": {
            "username": "vpn_tehran",
            "title": "V2rayNG \u0645\u0631\u06a9\u0632 \u062a\u062e\u0635\u0635\u06cc",
            "logo": "https:\/\/raw.githubusercontent.com\/alihusainsorathiya\/v2gram\/main\/modules\/channels\/vpn_tehran.jpg"
        },
        "type": "vless",
        "config": "vless:\/\/e4824193-4f54-453b-d037-88368e85ef0e@45.82.251.78:8880?mode=gun&amp;security=none&amp;encryption=none&amp;type=grpc&amp;serviceName=#@vpn_tehran| AHS -\ud83c\udde8\ud83c\uddfe|11.86",
        "time": "2025-08-11 02:56:26"
    },
    {
        "channel": {
            "username": "vpn_tehran",
            "title": "V2rayNG \u0645\u0631\u06a9\u0632 \u062a\u062e\u0635\u0635\u06cc",
            "logo": "https:\/\/raw.githubusercontent.com\/alihusainsorathiya\/v2gram\/main\/modules\/channels\/vpn_tehran.jpg"
        },
        "type": "vless",
        "config": "vless:\/\/2036e2c3-18a5-4eed-9db4-f91a7f02c7d5@45.131.4.85:80?path=\/193.123.81.105=443&amp;security=none&amp;encryption=none&amp;host=zoomgov.vipren.biz.id&amp;type=ws#@vpn_tehran| AHS -\ud83c\uddf3\ud83c\uddf1|5.33",
        "time": "2025-08-11 02:56:26"
    },
    {
        "channel": {
            "username": "vpn_tehran",
            "title": "V2rayNG \u0645\u0631\u06a9\u0632 \u062a\u062e\u0635\u0635\u06cc",
            "logo": "https:\/\/raw.githubusercontent.com\/alihusainsorathiya\/v2gram\/main\/modules\/channels\/vpn_tehran.jpg"
        },
        "type": "vless",
        "config": "vless:\/\/e4824193-4f54-453b-d037-88368e85ef0e@45.82.251.58:8880?mode=gun&amp;security=none&amp;encryption=none&amp;type=grpc&amp;serviceName=#@vpn_tehran| AHS -\ud83c\udde8\ud83c\uddfe|11.53",
        "time": "2025-08-11 02:56:26"
    },
    {
        "channel": {
            "username": "lrnbymaa",
            "title": "Lrn By MAA",
            "logo": "https:\/\/raw.githubusercontent.com\/alihusainsorathiya\/v2gram\/main\/modules\/channels\/lrnbymaa.jpg"
        },
        "type": "vless",
        "config": "vless:\/\/4390049a-814c-4a60-a6a5-0ce8d0c87c55@172.66.40.99:8080?path=\/telegram-CONFiGLiNE,telegram-CONFiGLiNE,telegram-CONFiGLiNE,telegram-CONFiGLiNE,telegram-CONFiGLiNE,telegram-CONFiGLiNE,telegram-CONFiGLiNE,telegram-CONFiGLiNE?ed=80&amp;security=none&amp;encryption=none&amp;host=nlnew.motorphrotan.ir&amp;type=ws#@lrnbymaa| AHS -\ud83d\udea9|5.43",
        "time": "2025-08-11 02:56:24"
    },
    {
        "channel": {
            "username": "lrnbymaa",
            "title": "Lrn By MAA",
            "logo": "https:\/\/raw.githubusercontent.com\/alihusainsorathiya\/v2gram\/main\/modules\/channels\/lrnbymaa.jpg"
        },
        "type": "vless",
        "config": "vless:\/\/4390049a-814c-4a60-a6a5-0ce8d0c87c55@172.66.40.99:8080?path=\/telegram-CONFiGLiNE,telegram-CONFiGLiNE,telegram-CONFiGLiNE,telegram-CONFiGLiNE,telegram-CONFiGLiNE,telegram-CONFiGLiNE,telegram-CONFiGLiNE,telegram\u2026#@lrnbymaa| AHS -\ud83d\udea9|5.42",
        "time": "2025-08-11 02:56:24"
    },
    {
        "channel": {
            "username": "lrnbymaa",
            "title": "Lrn By MAA",
            "logo": "https:\/\/raw.githubusercontent.com\/alihusainsorathiya\/v2gram\/main\/modules\/channels\/lrnbymaa.jpg"
        },
        "type": "vless",
        "config": "vless:\/\/1003-HqV2rayNG@Mci-mmnoon.r-sgoone.ir:80?security=none&amp;encryption=none&amp;type=httpupgrade#@lrnbymaa| AHS -\ud83d\udea9|7.23",
        "time": "2025-08-11 02:56:24"
    },
    {
        "channel": {
            "username": "VmessProtocol",
            "title": "V2ray Vless | \u0641\u06cc\u0644\u062a\u0631\u0634\u06a9\u0646 | \u0633\u0631\u0648\u0631 \u0627\u062e\u062a\u0635\u0627\u0635\u06cc",
            "logo": "https:\/\/raw.githubusercontent.com\/alihusainsorathiya\/v2gram\/main\/modules\/channels\/VmessProtocol.jpg"
        },
        "type": "vless",
        "config": "vless:\/\/c313c27c-97ff-45ed-ab5c-64641af5debc@fierce-data.seotoolsforyou.co.uk:80?encryption=none&amp;security=none&amp;type=ws&amp;path=\/#@VmessProtocol| AHS -\ud83d\udea9|6.2",
        "time": "2025-08-11 02:56:14"
    },
    {
        "channel": {
            "username": "VmessProtocol",
            "title": "V2ray Vless | \u0641\u06cc\u0644\u062a\u0631\u0634\u06a9\u0646 | \u0633\u0631\u0648\u0631 \u0627\u062e\u062a\u0635\u0627\u0635\u06cc",
            "logo": "https:\/\/raw.githubusercontent.com\/alihusainsorathiya\/v2gram\/main\/modules\/channels\/VmessProtocol.jpg"
        },
        "type": "vless",
        "config": "vless:\/\/df0680ca-e43c-498d-ed86-8e196eedd012@185.231.205.231:8880?encryption=none&amp;security=none&amp;type=grpc#@VmessProtocol| AHS -\ud83c\uddeb\ud83c\uddf7|80.81",
        "time": "2025-08-11 02:56:14"
    },
    {
        "channel": {
            "username": "VmessProtocol",
            "title": "V2ray Vless | \u0641\u06cc\u0644\u062a\u0631\u0634\u06a9\u0646 | \u0633\u0631\u0648\u0631 \u0627\u062e\u062a\u0635\u0627\u0635\u06cc",
            "logo": "https:\/\/raw.githubusercontent.com\/alihusainsorathiya\/v2gram\/main\/modules\/channels\/VmessProtocol.jpg"
        },
        "type": "vless",
        "config": "vless:\/\/0fbf4f81-2598-4b6a-a623-0ead4cb9efa8@privasi.turah.my.id:443?encryption=none&amp;security=tls&amp;sni=privasi.turah.my.id&amp;fp=chrome&amp;type=ws&amp;host=privasi.turah.my.id&amp;path=\/Free-CF-Proxy-AD192.3.113.4-19318#@VmessProtocol| AHS -\ud83d\udea9|6.14",
        "time": "2025-08-11 02:56:14"
    },
    {
        "channel": {
            "username": "vless_vmess",
            "title": "vless_vmess",
            "logo": "https:\/\/raw.githubusercontent.com\/alihusainsorathiya\/v2gram\/main\/modules\/channels\/vless_vmess.jpg"
        },
        "type": "vless",
        "config": "vless:\/\/ccbe6b7c-9264-40c4-8bc1-ef8f6205d7a4@www.speedtest.net:8443?path=\/&amp;security=tls&amp;encryption=none&amp;host=hetzner-4.access.name.ng&amp;type=ws&amp;sni=hetzner-4.access.name.ng#@vless_vmess| AHS -\ud83d\udea9|13.64",
        "time": "2025-08-11 02:55:58"
    },
    {
        "channel": {
            "username": "v2ray_swhil",
            "title": "@v2ray_swhil",
            "logo": "https:\/\/raw.githubusercontent.com\/alihusainsorathiya\/v2gram\/main\/modules\/channels\/v2ray_swhil.jpg"
        },
        "type": "vless",
        "config": "vless:\/\/95dfa5f5-d47b-4629-a4f4-6a3f0b9ab052@104.17.234.128:443?path=\/Telegram,VPNCUSTOMIZE?ed=8080&amp;security=tls&amp;encryption=none&amp;alpn=h2,http\/1.1&amp;host=join.VPNCUSTOMIZE.www.speedtest.net.ovh.Powerfullserver.de&amp;fp=randomized&amp;type=ws&amp;sni=join.VPNCUSTOMIZE.www.speedtest.net.ovh.Powerfullserver.de#@v2ray_swhil| AHS -\ud83d\udea9|5.49",
        "time": "2025-08-11 02:55:45"
    },
    {
        "channel": {
            "username": "v2ray_swhil",
            "title": "@v2ray_swhil",
            "logo": "https:\/\/raw.githubusercontent.com\/alihusainsorathiya\/v2gram\/main\/modules\/channels\/v2ray_swhil.jpg"
        },
        "type": "vless",
        "config": "vless:\/\/telegram-id-ArV2ray@151.101.194.133:443?encryption=none&amp;security=tls&amp;sni=mio.splashthat.com&amp;alpn=h2,http\/1.1&amp;fp=chrome&amp;type=ws&amp;host=Shuow10.net&amp;path=\/telegram-ArV2ray,telegram-ArV2ray,telegram-ArV2ray,telegram-ArV2ray,telegram-ArV2ray,telegram-ArV2ray,telegram-ArV2ray,telegram-ArV2ray,telegram-ArV2ray,telegram-ArV2ray?ed=2048#@v2ray_swhil| AHS -\ud83c\uddfa\ud83c\uddf8|5.36",
        "time": "2025-08-11 02:55:44"
    },
    {
        "channel": {
            "username": "NIM_VPN_ir",
            "title": "NIMVPN",
            "logo": "https:\/\/raw.githubusercontent.com\/alihusainsorathiya\/v2gram\/main\/modules\/channels\/NIM_VPN_ir.jpg"
        },
        "type": "vless",
        "config": "vless:\/\/c43b7819-008e-4863-aa20-9d3fc2935df8@star-dc.az9x99.ir:2083?encryption=none&amp;security=tls&amp;sni=star-cloud.az9x99.ir&amp;alpn=h2&amp;fp=random&amp;type=ws&amp;host=star-cloud.az9x99.ir&amp;path=?ed=2048#@NIM_VPN_ir| AHS -\ud83d\udea9|12.68",
        "time": "2025-08-11 02:55:26"
    },
    {
        "channel": {
            "username": "NIM_VPN_ir",
            "title": "NIMVPN",
            "logo": "https:\/\/raw.githubusercontent.com\/alihusainsorathiya\/v2gram\/main\/modules\/channels\/NIM_VPN_ir.jpg"
        },
        "type": "vless",
        "config": "vless:\/\/c43b7819-008e-4863-aa20-9d3fc2935df8@dl.fastsoft98.ir:443?encryption=none&amp;security=tls&amp;sni=dl.fastsoft98.ir&amp;alpn=h2&amp;fp=random&amp;type=ws&amp;host=dl.fastsoft98.ir&amp;path=?ed=2048#@NIM_VPN_ir| AHS -\ud83c\uddf3\ud83c\uddf1|97.16",
        "time": "2025-08-11 02:55:25"
    },
    {
        "channel": {
            "username": "NIM_VPN_ir",
            "title": "NIMVPN",
            "logo": "https:\/\/raw.githubusercontent.com\/alihusainsorathiya\/v2gram\/main\/modules\/channels\/NIM_VPN_ir.jpg"
        },
        "type": "vless",
        "config": "vless:\/\/c43b7819-008e-4863-aa20-9d3fc2935df8@star-cdn.soft98speedtest.ir:2053?encryption=none&amp;security=tls&amp;sni=dl.soft98speedtest.ir&amp;alpn=h2&amp;fp=random&amp;type=ws&amp;host=dl.soft98speedtest.ir&amp;path=?ed=2048#@NIM_VPN_ir| AHS -\ud83d\udea9|104.34",
        "time": "2025-08-11 02:55:25"
    },
    {
        "channel": {
            "username": "ShadowProxy66",
            "title": "ShadowProxy66",
            "logo": "https:\/\/raw.githubusercontent.com\/alihusainsorathiya\/v2gram\/main\/modules\/channels\/ShadowProxy66.jpg"
        },
        "type": "vmess",
        "config": "vmess:\/\/eyJhZGQiOiIxNTQuMjIzLjE5LjIzMSIsImFpZCI6IjAiLCJhbHBuIjoiIiwiZnAiOiIiLCJob3N0IjoiMTU0LjIyMy4xOS4yMzEiLCJpZCI6ImJmYjMyM2QzLTIzOWUtNGUxYi1iZmE4LTEzZjY4Mzg1OTMxZSIsIm5ldCI6IndzIiwicGF0aCI6IlwvIiwicG9ydCI6IjIwMDg2IiwicHMiOiJAU2hhZG93UHJveHk2NnwgQUhTIC1cdWQ4M2NcdWRkZmFcdWQ4M2NcdWRkZjh8OS42MiIsInNjeSI6ImF1dG8iLCJzbmkiOiIiLCJ0bHMiOiIiLCJ0eXBlIjoiYXV0byIsInYiOiIyIn0=",
        "time": "2025-08-11 02:55:18"
    },
    {
        "channel": {
            "username": "ShadowProxy66",
            "title": "ShadowProxy66",
            "logo": "https:\/\/raw.githubusercontent.com\/alihusainsorathiya\/v2gram\/main\/modules\/channels\/ShadowProxy66.jpg"
        },
        "type": "vmess",
        "config": "vmess:\/\/eyJhZGQiOiIyMTYuMTczLjY5LjI1MCIsImFpZCI6IjAiLCJhbHBuIjoiIiwiZnAiOiIiLCJob3N0IjoiIiwiaWQiOiI5MTM4MjA5Mi0yMzMwLTQ1NWItOGExYy05YzEyOWNmZTY2MWEiLCJuZXQiOiJ3cyIsInBhdGgiOiJcLyIsInBvcnQiOiI4NDQzIiwicHMiOiJAU2hhZG93UHJveHk2NnwgQUhTIC1cdWQ4M2NcdWRkZjFcdWQ4M2NcdWRkZmJ8MTExLjA3Iiwic2N5IjoiYXV0byIsInNuaSI6IiIsInRscyI6IiIsInR5cGUiOiJhdXRvIiwidiI6IjIifQ==",
        "time": "2025-08-11 02:55:18"
    },
    {
        "channel": {
            "username": "ShadowProxy66",
            "title": "ShadowProxy66",
            "logo": "https:\/\/raw.githubusercontent.com\/alihusainsorathiya\/v2gram\/main\/modules\/channels\/ShadowProxy66.jpg"
        },
        "type": "vmess",
        "config": "vmess:\/\/eyJhZGQiOiI0Ni4xNjUuMTk0LjkwIiwiYWlkIjoiMCIsImFscG4iOiIiLCJmcCI6IiIsImhvc3QiOiIiLCJpZCI6ImYyYTlmMTQ5LWNiNmEtNDY2OS05MDk3LTJkOGNiMmQ0ZWE3ZSIsIm5ldCI6IndzIiwicGF0aCI6IlwvIiwicG9ydCI6IjIwMDg2IiwicHMiOiJAU2hhZG93UHJveHk2NnwgQUhTIC1cdWQ4M2NcdWRkZTlcdWQ4M2NcdWRkZWF8OTMuMjgiLCJzY3kiOiJhdXRvIiwic25pIjoiIiwidGxzIjoiIiwidHlwZSI6ImF1dG8iLCJ2IjoiMiJ9",
        "time": "2025-08-11 02:55:17"
    },
    {
        "channel": {
            "username": "ShadowProxy66",
            "title": "ShadowProxy66",
            "logo": "https:\/\/raw.githubusercontent.com\/alihusainsorathiya\/v2gram\/main\/modules\/channels\/ShadowProxy66.jpg"
        },
        "type": "vless",
        "config": "vless:\/\/de7e69b8-c4e7-4461-f061-12f42115b51b@104.16.1.106:80?path=\/&amp;security=&amp;encryption=none&amp;host=eng.vinamarketcenter.ir&amp;type=ws#@ShadowProxy66| AHS -\ud83d\udea9|5.37",
        "time": "2025-08-11 02:55:16"
    },
    {
        "channel": {
            "username": "ShadowProxy66",
            "title": "ShadowProxy66",
            "logo": "https:\/\/raw.githubusercontent.com\/alihusainsorathiya\/v2gram\/main\/modules\/channels\/ShadowProxy66.jpg"
        },
        "type": "vless",
        "config": "vless:\/\/df0680ca-e43c-498d-ed86-8e196eedd012@185.231.205.253:8880?mode=gun&amp;security=&amp;encryption=none&amp;type=grpc#@ShadowProxy66| AHS -\ud83c\uddeb\ud83c\uddf7|81.04",
        "time": "2025-08-11 02:55:16"
    },
    {
        "channel": {
            "username": "ShadowProxy66",
            "title": "ShadowProxy66",
            "logo": "https:\/\/raw.githubusercontent.com\/alihusainsorathiya\/v2gram\/main\/modules\/channels\/ShadowProxy66.jpg"
        },
        "type": "vless",
        "config": "vless:\/\/d4992ec8-d781-45f5-9f59-ef8c769f46f9@185.234.66.101:443?path=\/hfwsxtws&amp;security=tls&amp;encryption=none&amp;host=TELEGRAM--ShadowProxy66&amp;type=ws#@ShadowProxy66| AHS -\ud83c\uddf2\ud83c\udde9|144.54",
        "time": "2025-08-11 02:55:15"
    },
    {
        "channel": {
            "username": "customv2ray",
            "title": "\u0633\u0631\u0648\u0631 \u06a9\u0627\u0646\u0641\u06cc\u06af|\u1d202\u0280\u1d00\u028f\ud83c\udf0f",
            "logo": "https:\/\/raw.githubusercontent.com\/alihusainsorathiya\/v2gram\/main\/modules\/channels\/customv2ray.jpg"
        },
        "type": "reality",
        "config": "vless:\/\/1068814a-6d43-40d9-a127-0f6b6b77ccfc@109.61.16.89:30938?security=reality&amp;encryption=none&amp;pbk=OkwhFGkP6NhXbmfBpBKqJ_HDNEcqbkp0mMc9HeYVBBE&amp;host=\/?BIA_TELEGRAM@MARAMBASHI_MARAMBASHI_MARAMBASHI&amp;headerType=none&amp;fp=random&amp;type=tcp&amp;flow=xtls-rprx-vision&amp;sni=indeed.com&amp;sid=9f2b1f07#REALITY|@customv2ray|\ud83c\udde9\ud83c\uddea|105.53",
        "time": "2025-08-11 02:55:03"
    },
    {
        "channel": {
            "username": "customv2ray",
            "title": "\u0633\u0631\u0648\u0631 \u06a9\u0627\u0646\u0641\u06cc\u06af|\u1d202\u0280\u1d00\u028f\ud83c\udf0f",
            "logo": "https:\/\/raw.githubusercontent.com\/alihusainsorathiya\/v2gram\/main\/modules\/channels\/customv2ray.jpg"
        },
        "type": "ss",
        "config": "ss:\/\/Y2hhY2hhMjAtaWV0Zi1wb2x5MTMwNTpvWklvQTY5UTh5aGNRVjhrYTNQYTNB@193.29.139.235:8080#@customv2ray| AHS -\ud83c\uddf3\ud83c\uddf1|86.18",
        "time": "2025-08-11 02:55:02"
    },
    {
        "channel": {
            "username": "customv2ray",
            "title": "\u0633\u0631\u0648\u0631 \u06a9\u0627\u0646\u0641\u06cc\u06af|\u1d202\u0280\u1d00\u028f\ud83c\udf0f",
            "logo": "https:\/\/raw.githubusercontent.com\/alihusainsorathiya\/v2gram\/main\/modules\/channels\/customv2ray.jpg"
        },
        "type": "ss",
        "config": "ss:\/\/Y2hhY2hhMjAtaWV0Zi1wb2x5MTMwNTpZWGdTOENvbVRhbTdxb2VzUGx6bE1v@83.147.216.70:64519#@customv2ray| AHS -\ud83c\uddeb\ud83c\uddee|110.73",
        "time": "2025-08-11 02:55:01"
    },
    {
        "channel": {
            "username": "v2rayngvpn",
            "title": "\u06a9\u0627\u0646\u0641\u06cc\u06af \u067e\u0631\u0648\u06a9\u0633\u06cc \u0641\u06cc\u0644\u062a\u0631\u0634\u06a9\u0646 \u0634\u06a9\u0646",
            "logo": "https:\/\/raw.githubusercontent.com\/alihusainsorathiya\/v2gram\/main\/modules\/channels\/v2rayngvpn.jpg"
        },
        "type": "vless",
        "config": "vless:\/\/ad02ae5c-55a7-4814-a58d-8da260ce7377@www.speedtest.net:80?path=\/@%43%55%53%54OMIZEROBOT---@%43%55%53%54OMIZEROBOT---@%43%55%53%54OMIZEROBOT---@%43%55%53%54OMIZEROBOT\/www.speedtest.net?ed=2080#=%40&amp;security=none&amp;encryption=none&amp;host=s1.VPNCUSTOMIZE.dNs-dynamic.neT.&amp;type=ws#@v2rayngvpn| AHS -\ud83d\udea9|14.04",
        "time": "2025-08-11 02:54:58"
    },
    {
        "channel": {
            "username": "v2rayngvpn",
            "title": "\u06a9\u0627\u0646\u0641\u06cc\u06af \u067e\u0631\u0648\u06a9\u0633\u06cc \u0641\u06cc\u0644\u062a\u0631\u0634\u06a9\u0646 \u0634\u06a9\u0646",
            "logo": "https:\/\/raw.githubusercontent.com\/alihusainsorathiya\/v2gram\/main\/modules\/channels\/v2rayngvpn.jpg"
        },
        "type": "vless",
        "config": "vless:\/\/7e948e09-fa6f-4b8e-8c5d-181fa15fbec5@104.17.41.52:8080?security=none&amp;encryption=none&amp;host=v2ngsupply2.ip-ddns.com&amp;type=ws#@v2rayngvpn| AHS -\ud83d\udea9|5.56",
        "time": "2025-08-11 02:54:58"
    },
    {
        "channel": {
            "username": "v2rayngvpn",
            "title": "\u06a9\u0627\u0646\u0641\u06cc\u06af \u067e\u0631\u0648\u06a9\u0633\u06cc \u0641\u06cc\u0644\u062a\u0631\u0634\u06a9\u0646 \u0634\u06a9\u0646",
            "logo": "https:\/\/raw.githubusercontent.com\/alihusainsorathiya\/v2gram\/main\/modules\/channels\/v2rayngvpn.jpg"
        },
        "type": "vless",
        "config": "vless:\/\/7a80a8d9-92f9-4f0a-8352-9005a8215ab8@transferwise.com:443?path=\/@Rayan_Config&amp;security=tls&amp;encryption=none&amp;host=rayan-d08.leila.dpdns.org&amp;fp=chrome&amp;type=ws&amp;sni=rAyAn-d08.lEiLa.dPdNs.oRG#@v2rayngvpn| AHS -\ud83d\udea9|42.82",
        "time": "2025-08-11 02:54:58"
    },
    {
        "channel": {
            "username": "v2rayNG_Matsuri",
            "title": "\u06a9\u0627\u0646\u0641\u06cc\u06af \u0647\u0627\u06cc \u0633\u0631\u062d\u0627\u0644 \u0631\u0627\u06cc\u06af\u0627\u0646 V2ray",
            "logo": "https:\/\/raw.githubusercontent.com\/alihusainsorathiya\/v2gram\/main\/modules\/channels\/v2rayNG_Matsuri.jpg"
        },
        "type": "reality",
        "config": "vless:\/\/Telegram--SRCVPN--@91.107.185.96:3090?mode=gun&amp;security=reality&amp;encryption=none&amp;authority=-@SRCVPN---@SRCVPN---@SRCVPN---@SRCVPN---@SRCVPN---@SRCVPN---@SRCVPN---@SRCVPN---@SRCVPN---@SRCVPN---@SRCVPN---@SRCVPN---@SRCVPN---@SRCVPN---@SRCVPN---@SRCVPN&amp;pbk=ezDK7fd9ieu1_0tDnmurxVheIpDpXofzBRovR8nCtTI&amp;fp=chrome&amp;spx=\/&amp;type=grpc&amp;sni=journalofbigdata.springeropen.com&amp;sid=3078f8f691b6b4#REALITY|@v2rayNG_Matsuri|\ud83c\udde9\ud83c\uddea|95.09",
        "time": "2025-08-11 02:54:57"
    },
    {
        "channel": {
            "username": "vmessorg",
            "title": "\ud83d\ude80Vmess vpn\ud83d\ude80",
            "logo": "https:\/\/raw.githubusercontent.com\/alihusainsorathiya\/v2gram\/main\/modules\/channels\/vmessorg.jpg"
        },
        "type": "vless",
        "config": "vless:\/\/52bb1620-f57a-432d-b8fc-4db175ff3f63@cumhuriyet.com.tr:80?type=ws&amp;host=join-to-Vmessorg.sabadyt.ir&amp;path=\/@vmessorg----@vmessorg-----@vmessorg----@vmessorg----@vmessorg----@vmessorg----@vmessorg----@vmessorg----@vmessorg----@vmessorg----@vmessorg----@vmessorg?ed=2480&amp;security=none#@vmessorg| AHS -\ud83d\udea9|5.97",
        "time": "2025-08-11 02:54:55"
    },
    {
        "channel": {
            "username": "vmessorg",
            "title": "\ud83d\ude80Vmess vpn\ud83d\ude80",
            "logo": "https:\/\/raw.githubusercontent.com\/alihusainsorathiya\/v2gram\/main\/modules\/channels\/vmessorg.jpg"
        },
        "type": "vless",
        "config": "vless:\/\/52bb1620-f57a-432d-b8fc-4db175ff3f63@cumhuriyet.com.tr:80?type=ws&amp;host=join-to-Vmessorg.sabadyt.ir&amp;path=\/@vmessorg----@vmessorg-----@vmessorg----@vmessorg----@vmessorg----@vmessorg----@vmessorg----@vmessorg----@vmessorg----@vmessorg----@vmessorg----@vmessorg?ed=2480&amp;security=none#@vmessorg| AHS -\ud83d\udea9|6.21",
        "time": "2025-08-11 02:54:55"
    },
    {
        "channel": {
            "username": "vmessorg",
            "title": "\ud83d\ude80Vmess vpn\ud83d\ude80",
            "logo": "https:\/\/raw.githubusercontent.com\/alihusainsorathiya\/v2gram\/main\/modules\/channels\/vmessorg.jpg"
        },
        "type": "vless",
        "config": "vless:\/\/d1bf6696-c690-49d8-8af5-3ba51a55bd3b@cumhuriyet.com.tr:80?type=ws&amp;host=join-to-Vmessorg.sabadyt.ir&amp;path=\/@vmessorg----@vmessorg-----@vmessorg----@vmessorg----@vmessorg----@vmessorg----@vmessorg----@vmessorg----@vmessorg----@vmessorg----@vmessorg----@vmessorg?ed=2480&amp;security=none#@vmessorg| AHS -\ud83d\udea9|5.9",
        "time": "2025-08-11 02:54:55"
    },
    {
        "channel": {
            "username": "UnlimitedDev",
            "title": "Unlimited",
            "logo": "https:\/\/raw.githubusercontent.com\/alihusainsorathiya\/v2gram\/main\/modules\/channels\/UnlimitedDev.jpg"
        },
        "type": "vless",
        "config": "vless:\/\/973713d5-0560-4f1a-b6df-3702a4ab941e@www.speedtest.net:8080?type=ws&amp;host=join-to-unlimiteddev.sabadyt.ir&amp;path=\/@unlimiteddev----@unlimiteddev-----@unlimiteddev----@unlimiteddev----@unlimiteddev----@unlimiteddev----@unlimiteddev----@unlimiteddev----@unlimitedev----@unlimitedev----@unlimiteddev----@unlimiteddev?ed=2480#@UnlimitedDev| AHS -\ud83d\udea9|13.24",
        "time": "2025-08-11 02:54:54"
    },
    {
        "channel": {
            "username": "prrofile_purple",
            "title": "\u0633\u0631\u0648\u0631 - V2rayNG",
            "logo": "https:\/\/raw.githubusercontent.com\/alihusainsorathiya\/v2gram\/main\/modules\/channels\/prrofile_purple.jpg"
        },
        "type": "reality",
        "config": "vless:\/\/2b4f6be4-32b4-495c-82d1-4d3093e5ddad@85.9.204.21:23328?security=reality&amp;encryption=none&amp;pbk=Za4d7M22mOEGXV23Tkb_STUCIznMbtlUS89ZAaECjU0&amp;headerType=none&amp;fp=chrome&amp;type=tcp&amp;flow=xtls-rprx-vision&amp;sni=ilovepdf.com&amp;sid=1af22e9c44f798bc#REALITY|@prrofile_purple|\ud83c\uddeb\ud83c\uddee|91.2",
        "time": "2025-08-11 02:54:41"
    },
    {
        "channel": {
            "username": "Outline_Vpn",
            "title": "Outline Vpn",
            "logo": "https:\/\/raw.githubusercontent.com\/alihusainsorathiya\/v2gram\/main\/modules\/channels\/Outline_Vpn.jpg"
        },
        "type": "reality",
        "config": "vless:\/\/d8dd94fd-540e-461d-b5d4-acebef02c22a@45.133.251.77:34045?security=reality&amp;encryption=none&amp;pbk=cDaDzPr3PlS3NM8lreHZbdo-Mhqz8vMBzMSkHXhGIUA&amp;headerType=none&amp;type=tcp&amp;sni=visit-this-invitation-link-to-join-tg-enkelte-notif.ekt.me&amp;sid=e8ab71d0#REALITY|@Outline_Vpn|\ud83c\udde9\ud83c\uddea|92.82",
        "time": "2025-08-11 02:54:39"
    },
    {
        "channel": {
            "username": "Outline_Vpn",
            "title": "Outline Vpn",
            "logo": "https:\/\/raw.githubusercontent.com\/alihusainsorathiya\/v2gram\/main\/modules\/channels\/Outline_Vpn.jpg"
        },
        "type": "vless",
        "config": "vless:\/\/2036e2c3-18a5-4eed-9db4-f91a7f02c7d5@45.131.7.0:80?path=\/193.123.81.105=443&amp;security=none&amp;encryption=none&amp;host=zoomgov.vipren.biz.id&amp;type=ws#@Outline_Vpn| AHS -\ud83c\uddf3\ud83c\uddf1|5.48",
        "time": "2025-08-11 02:54:38"
    },
    {
        "channel": {
            "username": "V2rayNGn",
            "title": "v2raynGn | \u06a9\u0627\u0646\u0641\u06cc\u06af | VPN",
            "logo": "https:\/\/raw.githubusercontent.com\/alihusainsorathiya\/v2gram\/main\/modules\/channels\/V2rayNGn.jpg"
        },
        "type": "vless",
        "config": "vless:\/\/53fa8faf-ba4b-4322-9c69-a3e5b1555049@188.42.89.100:8880?path=\/Channel&amp;security=none&amp;encryption=none&amp;host=reedfree8mahsang2.redorg.ir&amp;type=ws#@V2rayNGn| AHS -\ud83c\uddf1\ud83c\uddfa|5.73",
        "time": "2025-08-11 02:54:22"
    },
    {
        "channel": {
            "username": "V2rayNGn",
            "title": "v2raynGn | \u06a9\u0627\u0646\u0641\u06cc\u06af | VPN",
            "logo": "https:\/\/raw.githubusercontent.com\/alihusainsorathiya\/v2gram\/main\/modules\/channels\/V2rayNGn.jpg"
        },
        "type": "vless",
        "config": "vless:\/\/53fa8faf-ba4b-4322-9c69-a3e5b1555049@5.10.214.123:8880?path=\/am@2\/?ed=2560&amp;security=none&amp;encryption=none&amp;host=reedfree8mahsang2.redorg.ir&amp;type=ws#@V2rayNGn| AHS -\ud83c\udde9\ud83c\uddea|5.52",
        "time": "2025-08-11 02:54:22"
    },
    {
        "channel": {
            "username": "V2rayNGn",
            "title": "v2raynGn | \u06a9\u0627\u0646\u0641\u06cc\u06af | VPN",
            "logo": "https:\/\/raw.githubusercontent.com\/alihusainsorathiya\/v2gram\/main\/modules\/channels\/V2rayNGn.jpg"
        },
        "type": "vless",
        "config": "vless:\/\/0a506a60-ae3e-499d-9cbd-ab003f9f3f3b@185.176.24.159:443?path=\/Telegram@V2ray_Alpha\/?ed=2560&amp;security=tls&amp;alpn=http\/1.1&amp;encryption=none&amp;host=freedom.zistarvinbiotech.ir&amp;fp=randomized&amp;type=ws&amp;sni=FREEDOm.ZiStarvInbioTeCh.ir#@V2rayNGn| AHS -\ud83c\uddf3\ud83c\uddf1|5.46",
        "time": "2025-08-11 02:54:21"
    },
    {
        "channel": {
            "username": "ConfigsHUB",
            "title": "\ud835\ude3e\ud835\ude64\ud835\ude63\ud835\ude5b\ud835\ude5e\ud835\ude5c\ud835\ude68\ud835\ude43\ud835\ude6a\ud835\ude57",
            "logo": "https:\/\/raw.githubusercontent.com\/alihusainsorathiya\/v2gram\/main\/modules\/channels\/ConfigsHUB.jpg"
        },
        "type": "vless",
        "config": "vless:\/\/2036e2c3-18a5-4eed-9db4-f91a7f02c7d5@45.131.7.0:80?path=\/193.123.81.105=443&amp;security=none&amp;encryption=none&amp;host=zoomgov.vipren.biz.id&amp;type=ws#@ConfigsHUB| AHS -\ud83c\uddf3\ud83c\uddf1|5.57",
        "time": "2025-08-11 02:54:20"
    },
    {
        "channel": {
            "username": "ConfigsHUB",
            "title": "\ud835\ude3e\ud835\ude64\ud835\ude63\ud835\ude5b\ud835\ude5e\ud835\ude5c\ud835\ude68\ud835\ude43\ud835\ude6a\ud835\ude57",
            "logo": "https:\/\/raw.githubusercontent.com\/alihusainsorathiya\/v2gram\/main\/modules\/channels\/ConfigsHUB.jpg"
        },
        "type": "trojan",
        "config": "trojan:\/\/f282b878-8711-45a1-8c69-5564172123c1@172.67.181.173:443?path=\/Stupid-World\/103.106.228.126-2053&amp;security=tls&amp;host=vpn.stupidworld.web.id&amp;fp=chrome&amp;type=ws&amp;sni=vpn.stupidworld.web.id#\ud83d\udea9|@ConfigsHUB| AHS -5.42",
        "time": "2025-08-11 02:47:52"
    },
    {
        "channel": {
            "username": "hope_net",
            "title": "\ud83d\udd4a Hope Net",
            "logo": "https:\/\/raw.githubusercontent.com\/alihusainsorathiya\/v2gram\/main\/modules\/channels\/hope_net.jpg"
        },
        "type": "vless",
        "config": "vless:\/\/6a5fb830-a114-410e-df1f-9c36f841dc41@151.101.128.155:80?security=none&amp;type=ws&amp;host=UNLIMITEDDEV.channel-telegram-1.ir&amp;path=@UnlimitedDev----@UnlimitedDev-----@UnlimitedDev----@UnlimitedDev----@UnlimitedDev----@UnlimitedDev----@UnlimitedDev----@UnlimitedDev----@UnlimitedDev----@UnlimitedDev----@UnlimitedDev----@UnlimitedDev?ed=2480#@hope_net| AHS -\ud83c\uddfa\ud83c\uddf8|5.5",
        "time": "2025-08-11 02:37:40"
    },
    {
        "channel": {
            "username": "vpnfail_v2ray",
            "title": "\ud83c\udf10 V2Ray Vmess Proxy \ud83e\udd77VPN.fail",
            "logo": "https:\/\/raw.githubusercontent.com\/alihusainsorathiya\/v2gram\/main\/modules\/channels\/vpnfail_v2ray.jpg"
        },
        "type": "vmess",
        "config": "vmess:\/\/eyJhZGQiOiIxNjEuMjQ4LjMwLjMiLCJhaWQiOjAsImhvc3QiOiIiLCJpZCI6IjEwMDZhOTI4LTIwMjEtNGEzYi1iZWI1LWQ1ODUzYzYyODFjNSIsIm5ldCI6IndzIiwicGF0aCI6IlwvIiwicG9ydCI6MjAwODYsInBzIjoiQHZwbmZhaWxfdjJyYXl8IEFIUyAtXHVkODNjXHVkZGZiXHVkODNjXHVkZGYzfDI1MC40MyIsInRscyI6IiIsInR5cGUiOiJhdXRvIiwic2VjdXJpdHkiOiJhdXRvIiwic2tpcC1jZXJ0LXZlcmlmeSI6dHJ1ZSwic25pIjoiIn0=",
        "time": "2025-08-11 02:15:04"
    },
    {
        "channel": {
            "username": "vpnfail_v2ray",
            "title": "\ud83c\udf10 V2Ray Vmess Proxy \ud83e\udd77VPN.fail",
            "logo": "https:\/\/raw.githubusercontent.com\/alihusainsorathiya\/v2gram\/main\/modules\/channels\/vpnfail_v2ray.jpg"
        },
        "type": "vmess",
        "config": "vmess:\/\/eyJhZGQiOiI4Mi4yOS4xMzIuOSIsImFpZCI6MCwiaG9zdCI6IiIsImlkIjoiYjJjNjFmNTMtYTM1OS00MjljLTkwMGUtMjU1ZjAyZGVmNmJlIiwibmV0Ijoid3MiLCJwYXRoIjoiXC8iLCJwb3J0IjoyMDA4NiwicHMiOiJAdnBuZmFpbF92MnJheXwgQUhTIC1cdWQ4M2NcdWRkZmFcdWQ4M2NcdWRkZjh8NjIuMjQiLCJ0bHMiOiIiLCJ0eXBlIjoiYXV0byIsInNlY3VyaXR5IjoiYXV0byIsInNraXAtY2VydC12ZXJpZnkiOnRydWUsInNuaSI6IiJ9",
        "time": "2025-08-11 01:27:04"
    },
    {
        "channel": {
            "username": "hope_net",
            "title": "\ud83d\udd4a Hope Net",
            "logo": "https:\/\/raw.githubusercontent.com\/alihusainsorathiya\/v2gram\/main\/modules\/channels\/hope_net.jpg"
        },
        "type": "vless",
        "config": "vless:\/\/59a200b8-d967-44b0-96e5-3a4f0984c123@151.101.0.155:80?security=none&amp;type=ws&amp;host=api.nhl14.ir&amp;path=\/telegram-NUFiLTER,telegram-NUFiLTER,telegram-NUFiLTER,telegram-NUFiLTER?ed=2048#@hope_net| AHS -\ud83c\uddfa\ud83c\uddf8|5.33",
        "time": "2025-08-11 00:37:38"
    },
    {
        "channel": {
            "username": "hope_net",
            "title": "\ud83d\udd4a Hope Net",
            "logo": "https:\/\/raw.githubusercontent.com\/alihusainsorathiya\/v2gram\/main\/modules\/channels\/hope_net.jpg"
        },
        "type": "vless",
        "config": "vless:\/\/2647e0f9-e7b2-45ce-b70a-145a550a8759@151.101.130.133:443?security=tls&amp;sni=live.wkrq.com&amp;type=ws&amp;host=hvcr4d5767yhub.com&amp;path=ws\/?ed=2048#@hope_net| AHS -\ud83c\uddfa\ud83c\uddf8|5.64",
        "time": "2025-08-10 23:37:37"
    },
    {
        "channel": {
            "username": "PrivateVPNs",
            "title": "V2ray | Vmess | Trojan | Vless",
            "logo": "https:\/\/raw.githubusercontent.com\/alihusainsorathiya\/v2gram\/main\/modules\/channels\/PrivateVPNs.jpg"
        },
        "type": "trojan",
        "config": "trojan:\/\/telegram-id-privatevpns@13.36.247.35:22222?security=tls&amp;alpn=http\/1.1&amp;headerType=none&amp;type=tcp&amp;sni=trojan.burgerip.co.uk#\ud83c\uddeb\ud83c\uddf7|@PrivateVPNs| AHS -84.22",
        "time": "2025-08-10 23:07:07"
    },
    {
        "channel": {
            "username": "DirectVPN",
            "title": "V2ray VPN",
            "logo": "https:\/\/raw.githubusercontent.com\/alihusainsorathiya\/v2gram\/main\/modules\/channels\/DirectVPN.jpg"
        },
        "type": "trojan",
        "config": "trojan:\/\/telegram-id-directvpn@13.36.247.35:22223?security=tls&amp;alpn=http\/1.1&amp;headerType=none&amp;type=tcp&amp;sni=trojan.burgerip.co.uk#\ud83c\uddeb\ud83c\uddf7|@DirectVPN| AHS -84.85",
        "time": "2025-08-10 23:07:04"
    },
    {
        "channel": {
            "username": "VlessConfig",
            "title": "Vless | Vmess | Trojan",
            "logo": "https:\/\/raw.githubusercontent.com\/alihusainsorathiya\/v2gram\/main\/modules\/channels\/VlessConfig.jpg"
        },
        "type": "vless",
        "config": "vless:\/\/05519058-d2ac-4f28-9e4a-2b2a1386749e@13.36.247.35:22224?type=ws&amp;security=tls&amp;path=\/telegram-channel-vlessconfig&amp;sni=trojan.burgerip.co.uk#@VlessConfig| AHS -\ud83c\uddeb\ud83c\uddf7|85.1",
        "time": "2025-08-10 23:07:02"
    },
    {
        "channel": {
            "username": "Helix_Servers",
            "title": "- HELIX -",
            "logo": "https:\/\/raw.githubusercontent.com\/alihusainsorathiya\/v2gram\/main\/modules\/channels\/Helix_Servers.jpg"
        },
        "type": "reality",
        "config": "vless:\/\/Own3dByHELiX@magazine.sentry-warrunner.xyz:443?mode=gun&amp;security=reality&amp;encryption=none&amp;pbk=UrGT7bAn2UND3kx81QHACf_6qReN8V6_o70kZerONk4&amp;fp=chrome&amp;type=grpc&amp;serviceName=Telegram-@HELIX_Servers-@HELIX_Servers-@HELIX_Servers-@HELIX_Servers-@HELIX_Servers-@HELIX_Servers-@HELIX_Servers-@HELIX_Servers-@HELIX_Servers-@HELIX_Servers-@HELIX_Servers-@HELIX_Servers-@HELIX_Servers-@HELIX_Servers-@HELIX_Servers-@HELIX_Servers-@HELIX_Servers&amp;sni=miro.com&amp;sid=1c547814#REALITY|@Helix_Servers|\ud83c\udde9\ud83c\uddea|109.65",
        "time": "2025-08-10 22:39:22"
    },
    {
        "channel": {
            "username": "VlessConfig",
            "title": "Vless | Vmess | Trojan",
            "logo": "https:\/\/raw.githubusercontent.com\/alihusainsorathiya\/v2gram\/main\/modules\/channels\/VlessConfig.jpg"
        },
        "type": "vless",
        "config": "vless:\/\/05519058-d2ac-4f28-9e4a-2b2a1386749e@15.188.153.82:22224?type=ws&amp;security=tls&amp;path=\/telegram-channel-vlessconfig&amp;sni=trojan.burgerip.co.uk#@VlessConfig| AHS -\ud83c\uddeb\ud83c\uddf7|84.67",
        "time": "2025-08-10 22:03:22"
    },
    {
        "channel": {
            "username": "DirectVPN",
            "title": "V2ray VPN",
            "logo": "https:\/\/raw.githubusercontent.com\/alihusainsorathiya\/v2gram\/main\/modules\/channels\/DirectVPN.jpg"
        },
        "type": "trojan",
        "config": "trojan:\/\/telegram-id-directvpn@15.188.153.82:22223?security=tls&amp;alpn=http\/1.1&amp;headerType=none&amp;type=tcp&amp;sni=trojan.burgerip.co.uk#\ud83c\uddeb\ud83c\uddf7|@DirectVPN| AHS -84.11",
        "time": "2025-08-10 22:03:21"
    },
    {
        "channel": {
            "username": "PrivateVPNs",
            "title": "V2ray | Vmess | Trojan | Vless",
            "logo": "https:\/\/raw.githubusercontent.com\/alihusainsorathiya\/v2gram\/main\/modules\/channels\/PrivateVPNs.jpg"
        },
        "type": "trojan",
        "config": "trojan:\/\/telegram-id-privatevpns@15.188.153.82:22222?security=tls&amp;alpn=http\/1.1&amp;headerType=none&amp;type=tcp&amp;sni=trojan.burgerip.co.uk#\ud83c\uddeb\ud83c\uddf7|@PrivateVPNs| AHS -85.64",
        "time": "2025-08-10 22:03:20"
    },
    {
        "channel": {
            "username": "VlessConfig",
            "title": "Vless | Vmess | Trojan",
            "logo": "https:\/\/raw.githubusercontent.com\/alihusainsorathiya\/v2gram\/main\/modules\/channels\/VlessConfig.jpg"
        },
        "type": "vless",
        "config": "vless:\/\/05519058-d2ac-4f28-9e4a-2b2a1386749e@63.178.100.140:22224?type=ws&amp;security=tls&amp;path=\/telegram-channel-vlessconfig&amp;sni=trojan.burgerip.co.uk#@VlessConfig| AHS -\ud83c\udde9\ud83c\uddea|93.04",
        "time": "2025-08-10 20:02:49"
    },
    {
        "channel": {
            "username": "DirectVPN",
            "title": "V2ray VPN",
            "logo": "https:\/\/raw.githubusercontent.com\/alihusainsorathiya\/v2gram\/main\/modules\/channels\/DirectVPN.jpg"
        },
        "type": "trojan",
        "config": "trojan:\/\/telegram-id-directvpn@63.178.100.140:22223?security=tls&amp;alpn=http\/1.1&amp;headerType=none&amp;type=tcp&amp;sni=trojan.burgerip.co.uk#\ud83c\udde9\ud83c\uddea|@DirectVPN| AHS -94.18",
        "time": "2025-08-10 20:02:48"
    },
    {
        "channel": {
            "username": "PrivateVPNs",
            "title": "V2ray | Vmess | Trojan | Vless",
            "logo": "https:\/\/raw.githubusercontent.com\/alihusainsorathiya\/v2gram\/main\/modules\/channels\/PrivateVPNs.jpg"
        },
        "type": "trojan",
        "config": "trojan:\/\/telegram-id-privatevpns@63.178.100.140:22222?security=tls&amp;alpn=http\/1.1&amp;headerType=none&amp;type=tcp&amp;sni=trojan.burgerip.co.uk#\ud83c\udde9\ud83c\uddea|@PrivateVPNs| AHS -89.99",
        "time": "2025-08-10 20:02:47"
    },
    {
        "channel": {
            "username": "UnlimitedDev",
            "title": "Unlimited",
            "logo": "https:\/\/raw.githubusercontent.com\/alihusainsorathiya\/v2gram\/main\/modules\/channels\/UnlimitedDev.jpg"
        },
        "type": "vless",
        "config": "vless:\/\/973713d5-0560-4f1a-b6df-3702a4ab941e@cumhuriyet.com.tr:8080?type=ws&amp;host=join-to-unlimiteddev.sabadyt.ir&amp;path=\/@unlimiteddev----@unlimiteddev-----@unlimiteddev----@unlimiteddev----@unlimiteddev----@unlimiteddev----@unlimiteddev----@unlimiteddev----@unlimitedev----@unlimitedev----@unlimiteddev----@unlimiteddev?ed=2480#@UnlimitedDev| AHS -\ud83d\udea9|6.21",
        "time": "2025-08-10 00:27:38"
    },
    {
        "channel": {
            "username": "fnet00",
            "title": "\ud83d\uddfd FNET00 | \u0647\u0645\u0647 \u0686\u06cc\u0632 \u0622\u0632\u0627\u062f \ud83e\udd0d",
            "logo": "https:\/\/raw.githubusercontent.com\/alihusainsorathiya\/v2gram\/main\/modules\/channels\/fnet00.jpg"
        },
        "type": "vless",
        "config": "vless:\/\/0417be58-2ea8-49de-8083-9eff9b0137e5@v2ray.codefyinc.com:443?path=\/vlessws&amp;security=tls&amp;encryption=none&amp;host=v2ray.codefyinc.com&amp;type=ws&amp;sni=v2ray.codefyinc.com#@fnet00| AHS -\ud83c\uddfa\ud83c\uddf8|52.81",
        "time": "2025-08-09 23:55:37"
    },
    {
        "channel": {
            "username": "vmess_vless_v2rayng",
            "title": "vmess vless v2rayng",
            "logo": "https:\/\/raw.githubusercontent.com\/alihusainsorathiya\/v2gram\/main\/modules\/channels\/vmess_vless_v2rayng.jpg"
        },
        "type": "ss",
        "config": "ss:\/\/Y2hhY2hhMjAtaWV0Zi1wb2x5MTMwNTpjdklJODVUclc2bjBPR3lmcEhWUzF1@45.87.175.171:8080#@vmess_vless_v2rayng| AHS -\ud83c\uddf1\ud83c\uddf9|85.51",
        "time": "2025-08-09 18:29:41"
    },
    {
        "channel": {
            "username": "UnlimitedDev",
            "title": "Unlimited",
            "logo": "https:\/\/raw.githubusercontent.com\/alihusainsorathiya\/v2gram\/main\/modules\/channels\/UnlimitedDev.jpg"
        },
        "type": "vless",
        "config": "vless:\/\/6b6c9ce9-0a23-4b1b-cd03-35493c801007@cumhuriyet.com.tr:8080?type=ws&amp;host=join-to-unlimiteddev.sabadyt.ir&amp;path=\/@unlimiteddev----@unlimiteddev-----@unlimiteddev----@unlimiteddev----@unlimiteddev----@unlimiteddev\u2026#@UnlimitedDev| AHS -\ud83d\udea9|6.31",
        "time": "2025-08-09 00:42:43"
    },
    {
        "channel": {
            "username": "proxystore11",
            "title": "\u06aa\u0627\u0646\u0641\u06cc\u06af\u200c\u06a9\u062f\u0647",
            "logo": "https:\/\/raw.githubusercontent.com\/alihusainsorathiya\/v2gram\/main\/modules\/channels\/proxystore11.jpg"
        },
        "type": "vless",
        "config": "vless:\/\/2f0f5525-5376-4820-a9b5-90064664a35d@soren1.mahmouditravelers.top:26779?mode=auto&amp;path=\/landing\/used\/?utm_source=DKHEADER&utm_medium=HEADERBTM&utm_campaign=DKHEADER-USED&utm_id=DK-HEADER-USEDLANDING&amp;security=none&amp;encryption=none&amp;host=digikala.com&amp;type=xhttp#@proxystore11| AHS -\ud83c\udde9\ud83c\uddea|552.25",
        "time": "2025-08-07 12:38:42"
    },
    {
        "channel": {
            "username": "vpn_tehran",
            "title": "V2rayNG \u0645\u0631\u06a9\u0632 \u062a\u062e\u0635\u0635\u06cc",
            "logo": "https:\/\/raw.githubusercontent.com\/alihusainsorathiya\/v2gram\/main\/modules\/channels\/vpn_tehran.jpg"
        },
        "type": "vmess",
        "config": "vmess:\/\/eyJhZGQiOiIyMTYuMTczLjY5LjI1MCIsImFpZCI6IjAiLCJhbHBuIjoiIiwiZnAiOiIiLCJob3N0IjoiIiwiaWQiOiI5MTM4MjA5Mi0yMzMwLTQ1NWItOGExYy05YzEyOWNmZTY2MWEiLCJuZXQiOiJ3cyIsInBhdGgiOiJcLyIsInBvcnQiOiI4NDQzIiwicHMiOiJAdnBuX3RlaHJhbnwgQUhTIC1cdWQ4M2NcdWRkZjFcdWQ4M2NcdWRkZmJ8MTExLjA0Iiwic2N5IjoiYXV0byIsInNuaSI6IiIsInRscyI6IiIsInR5cGUiOiIiLCJ2IjoiMiJ9",
        "time": "2025-08-05 20:51:25"
    },
    {
        "channel": {
            "username": "SafeNet_Server",
            "title": "SafeNet Server \ud83d\uddfd",
            "logo": "https:\/\/raw.githubusercontent.com\/alihusainsorathiya\/v2gram\/main\/modules\/channels\/SafeNet_Server.jpg"
        },
        "type": "vmess",
        "config": "vmess:\/\/eyJhZGQiOiJjdXN0b21lcnMudGVsZS1zaG9wLXRvby5zdHVkaW8iLCJhaWQiOiIwIiwiYWxwbiI6IiIsImZwIjoiIiwiaG9zdCI6IiIsImlkIjoiZWFhZTUyZDctYmMxYS00OTc5LWJkNjYtYjZiNDI4MTA3MTczIiwibmV0IjoidGNwIiwicGF0aCI6IiIsInBvcnQiOiIzMzIwMyIsInBzIjoiQFNhZmVOZXRfU2VydmVyfCBBSFMgLVx1ZDgzY1x1ZGRlOVx1ZDgzY1x1ZGRlYXwxOTUuNTYiLCJzY3kiOiJhdXRvIiwic25pIjoiIiwidGxzIjoiIiwidHlwZSI6Im5vbmUiLCJ2IjoiMiJ9",
        "time": "2025-08-05 16:28:24"
    },
    {
        "channel": {
            "username": "v2_team",
            "title": "\ud835\udde9\ud835\udfd0 | \ud835\udde7\ud835\uddd8\ud835\uddd4\ud835\udde0",
            "logo": "https:\/\/raw.githubusercontent.com\/alihusainsorathiya\/v2gram\/main\/modules\/channels\/v2_team.jpg"
        },
        "type": "reality",
        "config": "vless:\/\/21967761-73c8-4e93-8baf-adf41b072cfe@gr.globalunlimitedinternet.xyz:1911?mode=gun&amp;security=reality&amp;encryption=none&amp;pbk=VCwUyNFL_IMTZfEKeIUYEuXbPfzCpuUBGNW1kAu2VW4&amp;fp=chrome&amp;spx=\/grpc.reality&amp;type=grpc&amp;serviceName=grpc.reality&amp;sni=refersion.com&amp;sid=32aaf12b#REALITY|@v2_team|\ud83c\udde6\ud83c\uddea|129.6",
        "time": "2025-08-03 14:46:22"
    },
    {
        "channel": {
            "username": "SafeNet_Server",
            "title": "SafeNet Server \ud83d\uddfd",
            "logo": "https:\/\/raw.githubusercontent.com\/alihusainsorathiya\/v2gram\/main\/modules\/channels\/SafeNet_Server.jpg"
        },
        "type": "vless",
        "config": "vless:\/\/0fc95877-cdc3-458f-8b00-d554c99ecbfb@cb6.connectbaash.info:4406?security=none&amp;encryption=none&amp;host=www.varzesh3.com&amp;headerType=http&amp;type=tcp#@SafeNet_Server| AHS -\ud83c\uddee\ud83c\uddf7|291.06",
        "time": "2025-08-02 20:32:03"
    },
    {
        "channel": {
            "username": "free4allVPN",
            "title": "Shadowsocks Outline Vmess Open VPN",
            "logo": "https:\/\/raw.githubusercontent.com\/alihusainsorathiya\/v2gram\/main\/modules\/channels\/free4allVPN.jpg"
        },
        "type": "vmess",
        "config": "vmess:\/\/eyJhZGQiOiIyMTYuMTczLjY5LjI1MCIsImFpZCI6IjAiLCJhbHBuIjoiIiwiZnAiOiIiLCJob3N0IjoiIiwiaWQiOiI5MTM4MjA5Mi0yMzMwLTQ1NWItOGExYy05YzEyOWNmZTY2MWEiLCJuZXQiOiJ3cyIsInBhdGgiOiJcLyIsInBvcnQiOiI4NDQzIiwicHMiOiJAZnJlZTRhbGxWUE58IEFIUyAtXHVkODNjXHVkZGYxXHVkODNjXHVkZGZifDEwNi4xIiwic2N5IjoiYXV0byIsInNuaSI6IiIsInRscyI6IiIsInR5cGUiOiItLS0iLCJ2IjoiMiJ9",
        "time": "2025-07-30 01:22:06"
    },
    {
        "channel": {
            "username": "SafeNet_Server",
            "title": "SafeNet Server \ud83d\uddfd",
            "logo": "https:\/\/raw.githubusercontent.com\/alihusainsorathiya\/v2gram\/main\/modules\/channels\/SafeNet_Server.jpg"
        },
        "type": "vless",
        "config": "vless:\/\/d5f80b44-ee7b-4f51-c58d-137253ad5db6@xoxo.i-missvezze.ir:29262?security=none&amp;encryption=none&amp;host=fast.com&amp;headerType=http&amp;type=tcp#@SafeNet_Server| AHS -\ud83c\uddee\ud83c\uddf7|276.01",
        "time": "2025-07-27 08:39:30"
    },
    {
        "channel": {
            "username": "prrofile_purple",
            "title": "\u0633\u0631\u0648\u0631 - V2rayNG",
            "logo": "https:\/\/raw.githubusercontent.com\/alihusainsorathiya\/v2gram\/main\/modules\/channels\/prrofile_purple.jpg"
        },
        "type": "vmess",
        "config": "vmess:\/\/eyJhZGQiOiI1MS42OC4xOTEuMjMzIiwiYWlkIjoiMCIsImFscG4iOiIiLCJmcCI6IiIsImhvc3QiOiIiLCJpZCI6ImYwZWRhMDcyLTlhZTgtNDk0Yy1hNDk1LTIxNWZhNTcyOTQ2NyIsIm5ldCI6IndzIiwicGF0aCI6Ilwvdm1lc3NcLyIsInBvcnQiOiI4MCIsInBzIjoiQHBycm9maWxlX3B1cnBsZXwgQUhTIC1cdWQ4M2NcdWRkZWJcdWQ4M2NcdWRkZjd8OTMuODkiLCJzY3kiOiJhdXRvIiwic25pIjoiIiwidGxzIjoiIiwidHlwZSI6Ii0tLSIsInYiOiIyIn0=",
        "time": "2025-07-26 22:51:34"
    },
    {
        "channel": {
            "username": "vmess_vless_v2rayng",
            "title": "vmess vless v2rayng",
            "logo": "https:\/\/raw.githubusercontent.com\/alihusainsorathiya\/v2gram\/main\/modules\/channels\/vmess_vless_v2rayng.jpg"
        },
        "type": "ss",
        "config": "ss:\/\/Y2hhY2hhMjAtaWV0Zi1wb2x5MTMwNTpVbFQ4OUQwcnZjcjA1dEtmdDFOQjVh@83.147.216.70:64519#@vmess_vless_v2rayng| AHS -\ud83c\uddeb\ud83c\uddee|109.77",
        "time": "2025-07-25 09:59:05"
    },
    {
        "channel": {
            "username": "vmess_vless_v2rayng",
            "title": "vmess vless v2rayng",
            "logo": "https:\/\/raw.githubusercontent.com\/alihusainsorathiya\/v2gram\/main\/modules\/channels\/vmess_vless_v2rayng.jpg"
        },
        "type": "vless",
        "config": "vless:\/\/e9979910-79d1-4621-a93c-b2a579c44ba7@172.67.65.158:8880?path=\/Etb1L6YUdZFZuTOr?ed=2560&amp;security=none&amp;encryption=none&amp;host=VngSuPpLY.IP-Ddns.com&amp;type=ws#@vmess_vless_v2rayng| AHS -\ud83d\udea9|5.32",
        "time": "2025-07-22 15:34:27"
    },
    {
        "channel": {
            "username": "MsV2ray",
            "title": "\ud835\udc74\ud835\udc94\ud835\udc7d\ud835\udfe4\ud835\udc93\ud835\udc82\ud835\udc9a | \ud835\udc6a\ud835\udc90\ud835\udc8f\ud835\udc87\ud835\udc8a\ud835\udc88",
            "logo": "https:\/\/raw.githubusercontent.com\/alihusainsorathiya\/v2gram\/main\/modules\/channels\/MsV2ray.jpg"
        },
        "type": "vless",
        "config": "vless:\/\/MsV2ray-Telegram@www.speedtest.net:80?type=httpupgrade&amp;host=http-fast-de-speedtest.xqfactor.ir.&amp;path=\/MsV2ray?ed=80&amp;security=none#@MsV2ray| AHS -\ud83d\udea9|7.64",
        "time": "2025-07-21 22:45:48"
    },
    {
        "channel": {
            "username": "MsV2ray",
            "title": "\ud835\udc74\ud835\udc94\ud835\udc7d\ud835\udfe4\ud835\udc93\ud835\udc82\ud835\udc9a | \ud835\udc6a\ud835\udc90\ud835\udc8f\ud835\udc87\ud835\udc8a\ud835\udc88",
            "logo": "https:\/\/raw.githubusercontent.com\/alihusainsorathiya\/v2gram\/main\/modules\/channels\/MsV2ray.jpg"
        },
        "type": "vless",
        "config": "vless:\/\/MsV2ray-Telegram@www.speedtest.net:80?type=httpupgrade&amp;host=http-fast-de-speedtest.xqfactor.ir.&amp;path=\/MsV2ray?ed=80&amp;security=none#@MsV2ray| AHS -\ud83d\udea9|7.54",
        "time": "2025-07-21 22:26:03"
    },
    {
        "channel": {
            "username": "vmess_vless_v2rayng",
            "title": "vmess vless v2rayng",
            "logo": "https:\/\/raw.githubusercontent.com\/alihusainsorathiya\/v2gram\/main\/modules\/channels\/vmess_vless_v2rayng.jpg"
        },
        "type": "vless",
        "config": "vless:\/\/2036e2c3-18a5-4eed-9db4-f91a7f02c7d5@104.21.112.1:80?path=\/193.123.81.105=443&amp;security=none&amp;encryption=none&amp;host=zoomgov.vipren.biz.id&amp;type=ws#@vmess_vless_v2rayng| AHS -\ud83d\udea9|5.48",
        "time": "2025-07-20 13:20:24"
    },
    {
        "channel": {
            "username": "MsV2ray",
            "title": "\ud835\udc74\ud835\udc94\ud835\udc7d\ud835\udfe4\ud835\udc93\ud835\udc82\ud835\udc9a | \ud835\udc6a\ud835\udc90\ud835\udc8f\ud835\udc87\ud835\udc8a\ud835\udc88",
            "logo": "https:\/\/raw.githubusercontent.com\/alihusainsorathiya\/v2gram\/main\/modules\/channels\/MsV2ray.jpg"
        },
        "type": "vless",
        "config": "vless:\/\/Telegram-MsV2ray@www.speedtest.net:80?type=httpupgrade&amp;host=http-fast-de-speedtest.xqfactor.ir.&amp;path=\/MsV2ray?ed=80&amp;security=none#@MsV2ray| AHS -\ud83d\udea9|7.4",
        "time": "2025-07-19 14:39:49"
    },
    {
        "channel": {
            "username": "vmess_vless_v2rayng",
            "title": "vmess vless v2rayng",
            "logo": "https:\/\/raw.githubusercontent.com\/alihusainsorathiya\/v2gram\/main\/modules\/channels\/vmess_vless_v2rayng.jpg"
        },
        "type": "vless",
        "config": "vless:\/\/a396b860-11b7-4af3-9950-146caf79735e@172.66.47.61:8443?path=\/8WuhXm4QjK0L68Uf?ed=2560&amp;security=tls&amp;encryption=none&amp;host=gghdfa.pages.dev&amp;type=ws&amp;sni=gGHDFa.pAgeS.Dev#@vmess_vless_v2rayng| AHS -\ud83d\udea9|5.34",
        "time": "2025-07-19 08:55:54"
    },
    {
        "channel": {
            "username": "fnet00",
            "title": "\ud83d\uddfd FNET00 | \u0647\u0645\u0647 \u0686\u06cc\u0632 \u0622\u0632\u0627\u062f \ud83e\udd0d",
            "logo": "https:\/\/raw.githubusercontent.com\/alihusainsorathiya\/v2gram\/main\/modules\/channels\/fnet00.jpg"
        },
        "type": "vless",
        "config": "vless:\/\/bf3c99e7-68b4-4bad-b110-ebaf2ecab772@speedtest.net:80?type=xhttp&amp;path=\/admin?ed=2048&amp;host=speedy_lool.global.ssl.fastly.net&amp;mode=auto&amp;security=none#@fnet00| AHS -\ud83c\uddfa\ud83c\uddf8|6.11",
        "time": "2025-07-08 21:22:27"
    },
    {
        "channel": {
            "username": "vpn_proxy_custom",
            "title": "\ud80c\udda9\ud835\udc15\ud835\udc0f\ud835\udc0d[\ud83c\uddee\ud83c\uddf7]\ud835\udc08\ud835\udc11\ud835\udc00\ud835\udc0d\ud80c\uddaa",
            "logo": "https:\/\/raw.githubusercontent.com\/alihusainsorathiya\/v2gram\/main\/modules\/channels\/vpn_proxy_custom.jpg"
        },
        "type": "vless",
        "config": "vless:\/\/7c9e3c1d-a360-4429-9189-e45a98de7fde@add.ski1plag.ir:80?path=\/upload&amp;security=none&amp;encryption=none&amp;host=my.ski1plag.ir&amp;type=ws#@vpn_proxy_custom| AHS -\ud83d\udea9|215.51",
        "time": "2025-07-06 01:41:08"
    },
    {
        "channel": {
            "username": "vpn_proxy_custom",
            "title": "\ud80c\udda9\ud835\udc15\ud835\udc0f\ud835\udc0d[\ud83c\uddee\ud83c\uddf7]\ud835\udc08\ud835\udc11\ud835\udc00\ud835\udc0d\ud80c\uddaa",
            "logo": "https:\/\/raw.githubusercontent.com\/alihusainsorathiya\/v2gram\/main\/modules\/channels\/vpn_proxy_custom.jpg"
        },
        "type": "vless",
        "config": "vless:\/\/7c9e3c1d-a360-4429-9189-e45a98de7fde@add.ski1plag.ir:80?path=\/download&amp;security=none&amp;encryption=none&amp;host=my.ski1plag.ir&amp;type=ws#@vpn_proxy_custom| AHS -\ud83d\udea9|223.85",
        "time": "2025-07-03 15:38:34"
    },
    {
        "channel": {
            "username": "free4allVPN",
            "title": "Shadowsocks Outline Vmess Open VPN",
            "logo": "https:\/\/raw.githubusercontent.com\/alihusainsorathiya\/v2gram\/main\/modules\/channels\/free4allVPN.jpg"
        },
        "type": "vmess",
        "config": "vmess:\/\/eyJhZGQiOiI1MS43OS4xMDIuMjUzIiwiYWlkIjoiMCIsImFscG4iOiIiLCJmcCI6IiIsImhvc3QiOiI1MS43OS4xMDIuMjUzIiwiaWQiOiI1OGZlMTU0Mi01MjkwLTQwYWQtODE1YS03NzcwN2E4MWFmZTUiLCJuZXQiOiJ3cyIsInBhdGgiOiJcL0lPZWJoTE1obDFDVGJGSGJMOTVteWZSWDIiLCJwb3J0IjoiODAiLCJwcyI6IkBmcmVlNGFsbFZQTnwgQUhTIC1cdWQ4M2NcdWRkZThcdWQ4M2NcdWRkZTZ8MzQuMzMiLCJzY3kiOiJhdXRvIiwic25pIjoiIiwidGxzIjoiIiwidHlwZSI6Ii0tLSIsInYiOiIyIn0=",
        "time": "2025-06-29 22:41:06"
    },
    {
        "channel": {
            "username": "free4allVPN",
            "title": "Shadowsocks Outline Vmess Open VPN",
            "logo": "https:\/\/raw.githubusercontent.com\/alihusainsorathiya\/v2gram\/main\/modules\/channels\/free4allVPN.jpg"
        },
        "type": "ss",
        "config": "ss:\/\/YWVzLTEyOC1nY206c2hhZG93c29ja3M3@149.22.87.204:443#@free4allVPN| AHS -\ud83c\uddef\ud83c\uddf5|159.57",
        "time": "2025-06-29 22:30:07"
    },
    {
        "channel": {
            "username": "FalconPolV2rayNG",
            "title": "\u0633\u0631\u0648\u0631 \u0648\u06cc\u062a\u0648\u0631\u06cc| \u0627\u06cc\u0631\u062f\u0631\u0627\u067e",
            "logo": "https:\/\/raw.githubusercontent.com\/alihusainsorathiya\/v2gram\/main\/modules\/channels\/FalconPolV2rayNG.jpg"
        },
        "type": "vless",
        "config": "vless:\/\/53fa8faf-ba4b-4322-9c69-a3e5b1555049@www.speedtest.net:80?path=\/?ed=2560&amp;security=none&amp;encryption=none&amp;host=redfree8mahsang6.redfree8.ir&amp;type=ws#@FalconPolV2rayNG| AHS -\ud83d\udea9|14.03",
        "time": "2025-06-26 16:50:49"
    },
    {
        "channel": {
            "username": "FalconPolV2rayNG",
            "title": "\u0633\u0631\u0648\u0631 \u0648\u06cc\u062a\u0648\u0631\u06cc| \u0627\u06cc\u0631\u062f\u0631\u0627\u067e",
            "logo": "https:\/\/raw.githubusercontent.com\/alihusainsorathiya\/v2gram\/main\/modules\/channels\/FalconPolV2rayNG.jpg"
        },
        "type": "vless",
        "config": "vless:\/\/a7e4e5db-c120-4953-9926-c9e5ed7729b0@irt.oremote.org:16103?type=tcp&amp;path=\/lt&amp;host=divar.ir&amp;headerType=http&amp;security=none#@FalconPolV2rayNG| AHS -\ud83c\uddee\ud83c\uddf7|346.29",
        "time": "2025-06-17 21:13:30"
    },
    {
        "channel": {
            "username": "v2ray_confings2",
            "title": "V2ray\/vmess\/vless",
            "logo": "https:\/\/raw.githubusercontent.com\/alihusainsorathiya\/v2gram\/main\/modules\/channels\/v2ray_confings2.jpg"
        },
        "type": "vless",
        "config": "vless:\/\/c2c8a201-09b9-47a7-b336-fcf1657f54a8@172.66.44.75:443?path=\/TELEGRAM-MARAMBASHI\/?ed=2048&amp;security=tls&amp;encryption=none&amp;alpn=h2,http\/1.1&amp;host=bpb-worker-panel-3jc.pages.dev&amp;fp=randomized&amp;type=ws&amp;sni=bpb-wORKer-paNeL-3JC.pAgeS.DeV#@v2ray_confings2| AHS -\ud83d\udea9|5.58",
        "time": "2024-10-13 14:50:10"
    },
    {
        "channel": {
            "username": "v2ray_confings2",
            "title": "V2ray\/vmess\/vless",
            "logo": "https:\/\/raw.githubusercontent.com\/alihusainsorathiya\/v2gram\/main\/modules\/channels\/v2ray_confings2.jpg"
        },
        "type": "vless",
        "config": "vless:\/\/38720105-063f-40f5-a5eb-f3198b9b617d@172.66.44.233:443?path=\/Tel-@V2ray_Alpha\/?ed=2048&amp;security=tls&amp;encryption=none&amp;host=aksnmaioas.pages.dev&amp;fp=chrome&amp;type=ws&amp;sni=aksnmaioas.pages.dev#@v2ray_confings2| AHS -\ud83d\udea9|5.32",
        "time": "2024-10-13 14:49:19"
    },
    {
        "channel": {
            "username": "v2ray_confings2",
            "title": "V2ray\/vmess\/vless",
            "logo": "https:\/\/raw.githubusercontent.com\/alihusainsorathiya\/v2gram\/main\/modules\/channels\/v2ray_confings2.jpg"
        },
        "type": "vless",
        "config": "vless:\/\/c6d299d4-db0b-4444-8b56-b23bbdcbcd67@172.66.47.200:443?path=\/StDNeNqkbQxrj6Xy?ed=2560&amp;security=tls&amp;encryption=none&amp;alpn=h2,http\/1.1&amp;host=mIDsuMMer-bpb.PAgEs.DeV&amp;fp=randomized&amp;type=ws&amp;sni=midsUMmER-Bpb.pAgES.DEV#@v2ray_confings2| AHS -\ud83d\udea9|5.37",
        "time": "2024-10-13 14:49:12"
    },
    {
        "channel": {
            "username": "CloudCityy",
            "title": "Cloud City \u2601\ufe0f \ud83c\uddee\ud83c\uddf7",
            "logo": "https:\/\/raw.githubusercontent.com\/alihusainsorathiya\/v2gram\/main\/modules\/channels\/CloudCityy.jpg"
        },
        "type": "vless",
        "config": "vless:\/\/e71d08cf-7410-481f-b6d8-e7ef04015974@172.66.46.213:443?path=\/iD9iinktJHRPLLJu?ed=2560&amp;security=tls&amp;encryption=none&amp;alpn=h2,http\/1.1&amp;host=bARaRpOoR.pAgES.dEV&amp;fp=randomized&amp;type=ws&amp;sni=BArarPOor.pAGES.DeV#@CloudCityy| AHS -\ud83d\udea9|5.39",
        "time": "2024-09-29 00:02:14"
    },
    {
        "channel": {
            "username": "CloudCityy",
            "title": "Cloud City \u2601\ufe0f \ud83c\uddee\ud83c\uddf7",
            "logo": "https:\/\/raw.githubusercontent.com\/alihusainsorathiya\/v2gram\/main\/modules\/channels\/CloudCityy.jpg"
        },
        "type": "vless",
        "config": "vless:\/\/e71d08cf-7410-481f-b6d8-e7ef04015979@172.66.46.213:443?path=\/iD9iinktJHRPLLJu?ed=2560&amp;security=tls&amp;encryption=none&amp;alpn=h2,http\/1.1&amp;host=bARaRpOoR.pAgES.dEV&amp;fp=randomized&amp;type=ws&amp;sni=BArarPOor.pAGES.DeV#@CloudCityy| AHS -\ud83d\udea9|5.54",
        "time": "2024-09-21 14:55:37"
    },
    {
        "channel": {
            "username": "ovpn2",
            "title": "Open Vpn - \u0641\u06cc\u0644\u062a\u0631\u0634\u06a9\u0646",
            "logo": "https:\/\/raw.githubusercontent.com\/alihusainsorathiya\/v2gram\/main\/modules\/channels\/ovpn2.jpg"
        },
        "type": "trojan",
        "config": "trojan:\/\/dQDQCtns4R@162.159.138.232:443?security=tls&amp;sni=fadaei.movieland.top&amp;type=ws&amp;path=static34528&amp;host=fadaei.movieland.top#\ud83d\udea9|@ovpn2| AHS -5.42",
        "time": "2024-01-28 13:54:21"
    },
    {
        "channel": {
            "username": "ovpn2",
            "title": "Open Vpn - \u0641\u06cc\u0644\u062a\u0631\u0634\u06a9\u0646",
            "logo": "https:\/\/raw.githubusercontent.com\/alihusainsorathiya\/v2gram\/main\/modules\/channels\/ovpn2.jpg"
        },
        "type": "vless",
        "config": "vless:\/\/fedc279b-ccb3-4205-bb47-31ac79ae4e7a@162.159.138.232:443?security=tls&amp;sni=jenaei.movieland.top&amp;type=grpc&amp;serviceName=static43498&amp;encryption=none#@ovpn2| AHS -\ud83d\udea9|5.87",
        "time": "2024-01-28 13:38:18"
    },
    {
        "channel": {
            "username": "internet4iran",
            "title": "Internet4Iran",
            "logo": "https:\/\/raw.githubusercontent.com\/alihusainsorathiya\/v2gram\/main\/modules\/channels\/internet4iran.jpg"
        },
        "type": "reality",
        "config": "vless:\/\/a0660613-bab4-456f-91b7-b8923788ed3d@128.140.49.220:443?flow=xtls-rprx-vision&amp;type=tcp&amp;headerType=none&amp;security=reality&amp;fp=random&amp;sni=www.speedtest.net&amp;pbk=mNXhz9oVUOChfXonV3TJcv_IB1-epvPy0OXR--qY82E&amp;sid=758910ee7eab4a1b#REALITY|@internet4iran|\ud83c\udde9\ud83c\uddea|105.75",
        "time": "2023-08-23 13:02:08"
    },
    {
        "channel": {
            "username": "ProxyFn",
            "title": "ProxyFn \ud83d\udd25",
            "logo": "https:\/\/raw.githubusercontent.com\/alihusainsorathiya\/v2gram\/main\/modules\/channels\/ProxyFn.jpg"
        },
        "type": "reality",
        "config": "vless:\/\/cdb38f5b-12c3-414b-eacd-a635dc633701@193.168.144.46:443?mode=gun&amp;security=reality&amp;encryption=none&amp;pbk=rsoZpDByMW3Ukcj68I5vw_-k-CivE6CV6TPJxyPl6WY&amp;fp=chrome&amp;spx=\/storage&amp;type=grpc&amp;serviceName=&amp;sni=mega.io&amp;sid=07a9a22b#REALITY|@ProxyFn|\ud83c\udde8\ud83c\udded|90.42",
        "time": "2023-06-26 15:09:40"
    },
    {
        "channel": {
            "username": "v2rayvmess",
            "title": "\u06a9\u0627\u0646\u0641\u06cc\u0646\u06af \u0627\u06cc\u0646\u062c\u06a9\u062a\u0648\u0631 | \u0627\u0646\u062c\u06a9\u062a\u0648\u0631 V2rayng",
            "logo": "https:\/\/raw.githubusercontent.com\/alihusainsorathiya\/v2gram\/main\/modules\/channels\/v2rayvmess.jpg"
        },
        "type": "vmess",
        "config": "vmess:\/\/eyJhZGQiOiJpZC1sYi52aGF4Lm5ldCIsImFpZCI6IjAiLCJob3N0Ijoiem9vbS51cyIsImlkIjoiNmZlYTE2NDktNDI1Yi00MDkyLWJmNTMtMjk3OTIxNTJjOTI1IiwibmV0Ijoid3MiLCJwYXRoIjoiXC9zc2hraXRcL0Fyc2hhbTg1MjMxXC82MzQ3ZDA4MDIyYjkxXC8iLCJwb3J0IjoiODAiLCJwcyI6IkB2MnJheXZtZXNzfCBBSFMgLVx1ZDgzY1x1ZGRmYVx1ZDgzY1x1ZGRmOHw2LjEzIiwic2N5IjoiYXV0byIsInNuaSI6IiIsInRscyI6IiIsInR5cGUiOiIiLCJ2IjoiMiJ9",
        "time": "2022-10-23 01:29:45"
    }
]